scaled/__init__.py
scaled/about.py
scaled/client.py
scaled/cluster/__init__.py
scaled/cluster/cluster.py
scaled/cluster/combo.py
scaled/cluster/scheduler.py
scaled/entry_points/__init__.py
scaled/entry_points/cluster.py
scaled/entry_points/scheduler.py
scaled/entry_points/top.py
scaled/io/__init__.py
scaled/io/async_binder.py
scaled/io/async_connector.py
scaled/io/config.py
scaled/io/sync_connector.py
scaled/protocol/__init__.py
scaled/protocol/python/__init__.py
scaled/protocol/python/message.py
scaled/protocol/python/serializer/__init__.py
scaled/protocol/python/serializer/default.py
scaled/protocol/python/serializer/mixins.py
scaled/scheduler/__init__.py
scaled/scheduler/client_manager.py
scaled/scheduler/function_manager.py
scaled/scheduler/graph_manager.py
scaled/scheduler/main.py
scaled/scheduler/mixins.py
scaled/scheduler/status_reporter.py
scaled/scheduler/task_manager.py
scaled/scheduler/worker_manager.py
scaled/scheduler/allocators/__init__.py
scaled/scheduler/allocators/mixins.py
scaled/scheduler/allocators/queued.py
scaled/utility/__init__.py
scaled/utility/event_loop.py
scaled/utility/exceptions.py
scaled/utility/formatter.py
scaled/utility/key_value_set.py
scaled/utility/one_to_many_dict.py
scaled/utility/zmq_config.py
scaled/utility/logging/__init__.py
scaled/utility/logging/decorators.py
scaled/utility/logging/scoped_logger.py
scaled/utility/logging/utility.py
scaled/utility/queues/__init__.py
scaled/utility/queues/async_indexed_queue.py
scaled/utility/queues/async_priority_queue.py
scaled/worker/__init__.py
scaled/worker/worker.py
scaled/worker/agent/__init__.py
scaled/worker/agent/heartbeat_manager.py
scaled/worker/agent/mixins.py
scaled/worker/agent/processor_manager.py
scaled/worker/agent/task_manager.py
scaled/worker/agent/timeout_manager.py
scaled/worker/agent/processor/__init__.py
scaled/worker/agent/processor/cache_cleaner.py
scaled/worker/agent/processor/processor.py
scaled-1.0.2.dist-info/LICENSE
scaled-1.0.2.dist-info/METADATA
scaled-1.0.2.dist-info/WHEEL
scaled-1.0.2.dist-info/entry_points.txt
scaled-1.0.2.dist-info/top_level.txt
scaled-1.0.2.dist-info/RECORD
