Metadata-Version: 2.1
Name: scaled
Version: 1.0.2
Summary: Scale Distribution Framework
Author-email: Zhuo Yin <zhuoyin@gmail.com>
License: BSD-3-Clause
Project-URL: Home, https://github.com/scaled-distributed/scaled
Requires-Python: >=3.8
License-File: LICENSE
Requires-Dist: bidict
Requires-Dist: pyzmq
Requires-Dist: psutil
Requires-Dist: cloudpickle
Requires-Dist: tblib
Requires-Dist: graphlib-backport ; python_version < "3.9"
Provides-Extra: uvloop
Requires-Dist: uvloop ; extra == 'uvloop'
